btooth/__init__.py
btooth/btooth.py
btooth-0.0.1.dist-info/METADATA
btooth-0.0.1.dist-info/WHEEL
btooth-0.0.1.dist-info/top_level.txt
btooth-0.0.1.dist-info/RECORD
